README.rst
setup.py
simpletex/__init__.py
simpletex/base.py
simpletex/core.py
simpletex/document.py
simpletex/math.py
simpletex/sequences.py
simpletex.egg-info/PKG-INFO
simpletex.egg-info/SOURCES.txt
simpletex.egg-info/dependency_links.txt
simpletex.egg-info/top_level.txt
simpletex/formatting/__init__.py
simpletex/formatting/core.py
simpletex/formatting/font.py
simpletex/formatting/layout.py
simpletex/formatting/text.py
simpletex/registry/__init__.py
simpletex/registry/core.py
simpletex/registry/formatting.py