Metadata-Version: 1.1
Name: simpletex
Version: 0.2.3
Summary: Easy Latex Document Generation
Home-page: https://github.com/wgxli/simpletex
Author: Samuel Li
Author-email: samuel.wgx@gmail.com
License: UNKNOWN
Download-URL: https://github.com/wgxli/simpletex/archive/v0.2.3.tar.gz
Platform: UNKNOWN
